dodgem/__init__.py
dodgem/__main__.py
dodgem/dodgem.py
dodgem/dodgem_eval.json.gz
dodgem/gui.py
dodgem_game-1.0.0.dist-info/licenses/LICENSE
dodgem_game-1.0.0.dist-info/METADATA
dodgem_game-1.0.0.dist-info/WHEEL
dodgem_game-1.0.0.dist-info/entry_points.txt
dodgem_game-1.0.0.dist-info/top_level.txt
dodgem_game-1.0.0.dist-info/RECORD
