Metadata-Version: 2.4
Name: dodgem-game
Version: 1.0.0
Summary: Play and analyze the Dodgem game with CLI/GUI using an evaluation database
License: MIT License
Project-URL: Homepage, https://sekika.github.io/dodgem/
Project-URL: Documentation, https://sekika.github.io/dodgem-py/
Project-URL: Source, https://github.com/sekika/dodgem-py
Keywords: game,ai,search,mongodb,board-game,dodgem
Classifier: Programming Language :: Python :: 3
Classifier: Programming Language :: Python :: 3 :: Only
Classifier: Programming Language :: Python :: 3.10
Classifier: Programming Language :: Python :: 3.11
Classifier: Programming Language :: Python :: 3.12
Classifier: Operating System :: OS Independent
Classifier: Topic :: Games/Entertainment
Requires-Python: >=3.10
License-File: LICENSE
Requires-Dist: pymongo>=4
Dynamic: license-file
